{"blog_overview.md":"471ccf20","learn_pessimistic-rollup-with-a-shared-sequencer.md":"ad10734e","readme.md":"22ffdf2f","learn_overview.md":"dde54c4a","tutorials_full-and-sequencer-node.md":"db0df2c2","learn_based-pessimistic-rollup.md":"27944c10","tutorials_lazy-sequencing.md":"65b51c0f","learn_basic-rollup.md":"0c575b4b","tutorials_cosmwasm.md":"2f1d2264","tutorials_starter-rollup.md":"5681dd58","learn_about.md":"e6f28fa5","blog_introducing-rollkit.md":"f006044a","tutorials_recipe-book.md":"1f69e60d","learn_readme.md":"22a22a1f","blog_lets-roll-community-call.md":"d6db4f51","tutorials_wordle.md":"d554c339","learn_rollup-glossary.md":"2bdc49b7","tutorials_gm-world-testnet.md":"28f953a1","learn_intro.md":"76d88010","tutorials_gm-world-mainnet.md":"341aa795","tutorials_gm-world-frontend.md":"639c1e98","learn_transaction-flow.md":"d350be5e","learn_building-and-deploying-a-rollup.md":"c2ea8cda","tutorials_rollup-docker.md":"cd56860c","index.md":"a6024cd2","tutorials_restart-rollup.md":"34ba8450","tutorials_gm-world.md":"30fe1798","tutorials_bitcoin.md":"4c5aeeb3","tutorials_block-times.md":"23768910","tutorials_overview.md":"55d40087","tutorials_polaris-evm.md":"ffa490bc","blog_sovereign-rollups-on-bitcoin.md":"9812591b","learn_stack.md":"cbd3a2d3"}
