{"tutorials_gm-world-mainnet.md":"6669af93","index.md":"8073ecb1","readme.md":"2a2ea695","blog_overview.md":"0c18b9ec","learn_based-pessimistic-rollup.md":"1daf04a8","learn_overview.md":"b77d9829","learn_intro.md":"6cd65bd6","learn_building-and-deploying-a-rollup.md":"7edf963d","learn_pessimistic-rollup-with-a-shared-sequencer.md":"afcda34a","tutorials_full-and-sequencer-node.md":"040be6b8","learn_transaction-flow.md":"87984f4c","blog_sovereign-rollups-on-bitcoin.md":"29faa32a","tutorials_cosmwasm.md":"c255b5a7","blog_introducing-rollkit.md":"44850b2e","learn_rollup-glossary.md":"1d6ff22b","tutorials_gm-world-testnet.md":"01349e4f","tutorials_restart-rollup.md":"9c2a1a17","tutorials_gm-world.md":"292a6dcd","learn_readme.md":"d5cd446e","learn_stack.md":"33974a71","learn_about.md":"b883d67f","tutorials_overview.md":"24ab7855","tutorials_lazy-sequencing.md":"65c5bb29","tutorials_bitcoin.md":"da584828","blog_lets-roll-community-call.md":"bbfcd1b5","tutorials_wordle.md":"3a90b98d","tutorials_polaris-evm.md":"50d17650","learn_basic-rollup.md":"cf95b0bc","tutorials_block-times.md":"af19abea","tutorials_gm-world-frontend.md":"a6f1de75","tutorials_starter-rollup.md":"4d165533","tutorials_rollup-docker.md":"a3a76b82","tutorials_recipe-book.md":"a1d7ce7e"}
