{"readme.md":"f2253a0f","learn_transaction-flow.md":"19e58138","blog_introducing-rollkit.md":"bdd1a5e7","tutorials_polaris-evm.md":"7dccd655","tutorials_block-times.md":"1ade9c26","blog_lets-roll-community-call.md":"2c520556","learn_intro.md":"c597c2ff","blog_overview.md":"71403469","blog_sovereign-rollups-on-bitcoin.md":"362ace40","learn_about.md":"cdd5f81c","index.md":"2064fe81","tutorials_full-and-sequencer-node.md":"6e4de206","learn_rollup-glossary.md":"705e1474","learn_overview.md":"4b7c15ea","learn_readme.md":"b5b5dbe1","tutorials_overview.md":"558c52e9","tutorials_bitcoin.md":"638e8a2b","tutorials_lazy-sequencing.md":"5d8ebb1f","tutorials_rollup-docker.md":"4f64344c","tutorials_starter-rollup.md":"9129a542","learn_based-pessimistic-rollup.md":"f293e0a6","learn_pessimistic-rollup-with-a-shared-sequencer.md":"3c3bab74","learn_stack.md":"36bd038d","learn_basic-rollup.md":"3eecb930","tutorials_wordle.md":"6ea83389","tutorials_recipe-book.md":"e93acd1d","tutorials_cosmwasm.md":"d5349220","tutorials_restart-rollup.md":"e17785b2","tutorials_gm-world-frontend.md":"3b7534f0","tutorials_gm-world.md":"c83e27fe","learn_building-and-deploying-a-rollup.md":"d80f2ea3","tutorials_gm-world-mainnet.md":"07c297fc","tutorials_gm-world-testnet.md":"316f084e"}
