{"readme.md":"f2253a0f","tutorials_gm-world-frontend.md":"a3ea9838","learn_intro.md":"e1de304c","learn_overview.md":"8825ec72","learn_pessimistic-rollup-with-a-shared-sequencer.md":"6df9eab0","learn_rollup-glossary.md":"d68145c8","learn_stack.md":"2834fa4e","learn_transaction-flow.md":"56a35346","tutorials_bitcoin.md":"0799d0dd","tutorials_block-times.md":"efd1d3dc","tutorials_cosmwasm.md":"4e72fbf2","tutorials_full-and-sequencer-node.md":"f489eb20","blog_introducing-rollkit.md":"3380b4a9","blog_lets-roll-community-call.md":"8c1f5600","blog_overview.md":"ce6d14ff","blog_sovereign-rollups-on-bitcoin-with-rollkit.md":"9def51eb","learn_about.md":"cdd5f81c","learn_based-pessimistic-rollup.md":"f293e0a6","learn_basic-rollup.md":"3eecb930","learn_building-and-deploying-a-rollup.md":"7ebaef2f","learn_building-with-rollkit.md":"42e75a26","tutorials_gm-world.md":"37542623","tutorials_lazy-sequencing.md":"cbd1a046","tutorials_overview.md":"86f860d9","tutorials_recipe-book.md":"2f8f7a2c","tutorials_restart-rollup.md":"6eb1e472","tutorials_starter-rollup.md":"0e9f725c","tutorials_wordle.md":"f3877fd6","index.md":"9e6c4aa3","tutorials_rollup-docker.md":"4f64344c"}
