{"blog_lets-roll-community-call.md":"a5560039","readme.md":"dbb97afd","blog_overview.md":"00835552","blog_sovereign-rollups-on-bitcoin.md":"9b8698dd","blog_introducing-rollkit.md":"a397f4ab","learn_basic-rollup.md":"63e81181","index.md":"924288a9","learn_building-and-deploying-a-rollup.md":"94c24e62","learn_building-with-rollkit.md":"7dc138b7","learn_intro.md":"034b7b6d","learn_overview.md":"a2a42622","tutorials_bitcoin.md":"9d4d42ba","learn_rollup-glossary.md":"a894a26f","tutorials_block-times.md":"c356f4b6","learn_stack.md":"8de1ecc4","learn_pessimistic-rollup-with-a-shared-sequencer.md":"945b0ceb","learn_about.md":"d6d2d3e9","tutorials_cosmwasm.md":"b55401f8","tutorials_full-and-sequencer-node.md":"efc6d942","tutorials_gm-world-frontend.md":"bbf6fbbb","tutorials_gm-world.md":"75222d46","tutorials_lazy-sequencing.md":"e4bb2efb","tutorials_overview.md":"1402087c","tutorials_recipe-book.md":"7dfc04fe","tutorials_restart-rollup.md":"58b29205","tutorials_rollup-docker.md":"7d31170f","tutorials_wordle.md":"578e3131","learn_based-pessimistic-rollup.md":"e7bb8637","tutorials_starter-rollup.md":"daeed2be","learn_transaction-flow.md":"c43d2cba"}
